ksps/__init__.py
ksps/client.py
ksps/test.py
ksps-1.0.0.dist-info/METADATA
ksps-1.0.0.dist-info/WHEEL
ksps-1.0.0.dist-info/entry_points.txt
ksps-1.0.0.dist-info/licenses/LICENSE
ksps-1.0.0.dist-info/RECORD
