Metadata-Version: 2.4
Name: ksps
Version: 1.0.0
Summary: KPS - Ksmux Pub Sub: Client Python ultra-performant pour système pub/sub basé sur ksmux
Project-URL: Homepage, https://github.com/kamalshkeir/bbus
Project-URL: Repository, https://github.com/kamalshkeir/bbus
Project-URL: Documentation, https://github.com/kamalshkeir/bbus/blob/main/README.md
Author-email: Kamal Shkeir <kamalshkeir@gmail.com>
License: MIT
License-File: LICENSE
Keywords: asyncio,kamal,ksmux,ksps,messaging,pubsub,realtime,websocket
Classifier: Development Status :: 5 - Production/Stable
Classifier: Framework :: AsyncIO
Classifier: Intended Audience :: Developers
Classifier: License :: OSI Approved :: MIT License
Classifier: Programming Language :: Python :: 3
Classifier: Programming Language :: Python :: 3.11
Classifier: Programming Language :: Python :: 3.12
Classifier: Topic :: Internet :: WWW/HTTP :: Dynamic Content
Classifier: Topic :: Software Development :: Libraries :: Python Modules
Classifier: Topic :: System :: Networking
Requires-Python: >=3.11
Requires-Dist: orjson>=3.9.10
Requires-Dist: uvloop>=0.19.0; sys_platform != 'win32'
Requires-Dist: websockets>=12.0
Provides-Extra: all
Requires-Dist: aiofiles>=23.2.1; extra == 'all'
Requires-Dist: asyncio-mqtt>=0.16.1; extra == 'all'
Requires-Dist: black>=23.0.0; extra == 'all'
Requires-Dist: mypy>=1.5.0; extra == 'all'
Requires-Dist: pytest-asyncio>=0.21.0; extra == 'all'
Requires-Dist: pytest>=7.4.0; extra == 'all'
Requires-Dist: ruff>=0.1.0; extra == 'all'
Provides-Extra: dev
Requires-Dist: black>=23.0.0; extra == 'dev'
Requires-Dist: mypy>=1.5.0; extra == 'dev'
Requires-Dist: pytest-asyncio>=0.21.0; extra == 'dev'
Requires-Dist: pytest>=7.4.0; extra == 'dev'
Requires-Dist: ruff>=0.1.0; extra == 'dev'
Provides-Extra: files
Requires-Dist: aiofiles>=23.2.1; extra == 'files'
Provides-Extra: mqtt
Requires-Dist: asyncio-mqtt>=0.16.1; extra == 'mqtt'
